setup.cfg
setup.py
fancy/__init__.py
fancy.egg-info/PKG-INFO
fancy.egg-info/SOURCES.txt
fancy.egg-info/dependency_links.txt
fancy.egg-info/top_level.txt
fancy/analysis/__init__.py
fancy/analysis/analysis.py
fancy/analysis/results.py
fancy/detector/__init__.py
fancy/detector/auger2010.py
fancy/detector/auger2014.py
fancy/detector/detector.py
fancy/detector/exposure.py
fancy/interfaces/__init__.py
fancy/interfaces/data.py
fancy/interfaces/integration.py
fancy/interfaces/stan.py
fancy/plotting/HPD_regions.py
fancy/plotting/__init__.py
fancy/plotting/allskymap.py
fancy/plotting/colours.py
fancy/plotting/corner.py
fancy/propagation/__init__.py
fancy/propagation/energy_loss.py