Metadata-Version: 1.0
Name: fancy
Version: 3.0.0
Summary: Framework for the Analysis of Cosmic raYs
Home-page: https://github.com/cescalara/fancy
Author: Francesca Capel
Author-email: capel.francesca@gmail.com
License: UNKNOWN
Keywords: UHECR,analysis
Platform: UNKNOWN
